voidshred/__init__.py
voidshred/cli.py
voidshred-2.0.0.dist-info/licenses/LICENSE
voidshred-2.0.0.dist-info/METADATA
voidshred-2.0.0.dist-info/WHEEL
voidshred-2.0.0.dist-info/entry_points.txt
voidshred-2.0.0.dist-info/top_level.txt
voidshred-2.0.0.dist-info/RECORD
