Metadata-Version: 2.4
Name: voidshred
Version: 2.0.0
Summary: Secure file shredder
License: MIT
Requires-Python: >=3.8
License-File: LICENSE
Dynamic: license-file
